modelx/__init__.py
modelx/core/__init__.py
modelx/core/api.py
modelx/core/base.py
modelx/core/cells.py
modelx/core/chainmap.py
modelx/core/config.py
modelx/core/errors.py
modelx/core/formula.py
modelx/core/macro.py
modelx/core/model.py
modelx/core/node.py
modelx/core/parent.py
modelx/core/reference.py
modelx/core/space.py
modelx/core/system.py
modelx/core/util.py
modelx/core/views.py
modelx/core/binding/__init__.py
modelx/core/binding/boundfunc.py
modelx/core/binding/namespace.py
modelx/core/execution/__init__.py
modelx/core/execution/executor.py
modelx/core/execution/trace.py
modelx/export/__init__.py
modelx/export/_mx_sys.py
modelx/export/exporter.py
modelx/export/transformer.py
modelx/io/__init__.py
modelx/io/baseio.py
modelx/io/excel_legacy.py
modelx/io/excelio.py
modelx/io/moduleio.py
modelx/io/pandas.py
modelx/io/pandasio.py
modelx/managers/__init__.py
modelx/managers/component.py
modelx/managers/dummy.py
modelx/managers/inheritance.py
modelx/serialize/__init__.py
modelx/serialize/custom_pickle.py
modelx/serialize/deserializer.py
modelx/serialize/jsonvalues.py
modelx/serialize/pandas_compat.py
modelx/serialize/serializer_1.py
modelx/serialize/serializer_2.py
modelx/serialize/serializer_3.py
modelx/serialize/serializer_4.py
modelx/serialize/serializer_5.py
modelx/serialize/serializer_6.py
modelx/serialize/ziputil.py
modelx/testing/__init__.py
modelx/testing/testutil.py
modelx-0.30.1.dist-info/licenses/LICENSE.GPL.txt
modelx-0.30.1.dist-info/licenses/LICENSE.txt
modelx-0.30.1.dist-info/METADATA
modelx-0.30.1.dist-info/WHEEL
modelx-0.30.1.dist-info/top_level.txt
modelx-0.30.1.dist-info/RECORD
